pisahkan_ktp/__init__.py
pisahkan_ktp/ktp_segmenter.py
pisahkan_ktp-0.2.11.dist-info/LICENSE
pisahkan_ktp-0.2.11.dist-info/METADATA
pisahkan_ktp-0.2.11.dist-info/WHEEL
pisahkan_ktp-0.2.11.dist-info/RECORD
