Metadata-Version: 2.1
Name: pisahkan-ktp
Version: 0.2.11
Summary: Python package for detecting entities in text based on a dictionary and fuzzy similarity
Home-page: https://github.com/hanifabd/pisahkan-ktp
Keywords: ktp,segmentation,segmentasi,id-card,identity-card
Author: Hanif Yuli Abdillah P
Author-email: hanifabd23@gmail.com
Requires-Python: >=3.7
Classifier: License :: OSI Approved :: MIT License
Classifier: Operating System :: OS Independent
Classifier: Programming Language :: Python :: 3
Classifier: Programming Language :: Python :: 3.7
Classifier: Programming Language :: Python :: 3.8
Classifier: Programming Language :: Python :: 3.9
Classifier: Programming Language :: Python :: 3.10
Classifier: Programming Language :: Python :: 3.11
Classifier: Programming Language :: Python :: 3.12
Requires-Dist: opencv-contrib-python (==4.9.0.80)
Requires-Dist: opencv-python (==4.8.0.76)
Requires-Dist: pythonRLSA (==1.0.0)
Project-URL: Repository, https://github.com/hanifabd/pisahkan-ktp
